config/__init__.py
config/report/ConfigReporter.py
config/report/__init__.py
config/report/holder/ConfigReporterHolder.py
config/report/holder/__init__.py
persuader_technology_automata_config-0.1.6.dist-info/LICENSE
persuader_technology_automata_config-0.1.6.dist-info/METADATA
persuader_technology_automata_config-0.1.6.dist-info/WHEEL
persuader_technology_automata_config-0.1.6.dist-info/top_level.txt
persuader_technology_automata_config-0.1.6.dist-info/RECORD
