Metadata-Version: 2.1
Name: persuader-technology-automata-config
Version: 0.1.6
Summary: Automata Config
Author: Persuader Technology
Author-email: software@persuader.technology
License: UNLICENSE
Classifier: Programming Language :: Python :: 3
License-File: LICENSE
Requires-Dist: persuader-technology-automata-core (>=0.6.0)
Requires-Dist: persuader-technology-automata-logger (>=0.0.5)
Requires-Dist: persuader-technology-automata-missing-repository (>=0.2.1)
